{
  "interactionModel": {
    "languageModel": {
      "invocationName": "faq skill set",
      "intents": [
        {
          "name": "AMAZON.CancelIntent",
          "samples": []
        },
        {
          "name": "AMAZON.HelpIntent",
          "samples": []
        },
        {
          "name": "AMAZON.StopIntent",
          "samples": []
        },
        {
          "name": "AMAZON.NavigateHomeIntent",
          "samples": []
        },
        {
          "name": "AMAZON.FallbackIntent",
          "samples": []
        },
        {
          "name": "OpenFAQ",
          "slots": [],
          "samples": [
            "Alexa please open FAQ",
            "open Frequently Asked Questions",
            "open FAQ",
            "FAQ",
            "Hey Alexa open FAQ"
          ]
        },
        {
          "name": "QuestionIntent",
          "slots": [
            {
              "name": "question",
              "type": "AMAZON.CreativeWorkType"
            }
          ],
          "samples": [
            "Alexa how to {question}",
            "how to {question}",
            "Alexa where is {question}",
            "where is {question}",
            "Alexa how many {question}",
            "how many {question}",
            "Alexa when is {question}",
            "when is {question}",
            "what is {question}",
            "Alexa what is {question}"
          ]
        }
      ],
      "types": []
    }
  },
  "version": "7"
}